gmmePylib/__init__.py
gmmePylib/BatchApp-template.py
gmmePylib/BatchApp.py
gmmePylib/Utils/__init__.py
gmmePylib/Utils/CEC.py
gmmePylib/Utils/CmdLine.py
gmmePylib/Utils/Logger.py
gmmePylib/Utils/Mail.py
gmmePylib/Utils/Object.py
gmmePylib/Utils/os/__init__.py
gmmePylib/Utils/os/linux.py
gmmePylib/Utils/os/windows.py
gmmePylib/Utils/Other.py
gmmepylib-0.15.4.dist-info/METADATA
gmmepylib-0.15.4.dist-info/WHEEL
gmmepylib-0.15.4.dist-info/RECORD
