Metadata-Version: 2.3
Name: gmmepylib
Version: 0.15.4
Summary: GMME Libs for Python
License: file = "GMME_Software_License.txt
Author: David Crickenberger
Author-email: dcrick@gmm-enterprises.com
Requires-Python: >=3.11
Classifier: License :: Other/Proprietary License
Classifier: Programming Language :: Python :: 3
Classifier: Programming Language :: Python :: 3.11
Classifier: Programming Language :: Python :: 3.12
Classifier: Programming Language :: Python :: 3.13
Classifier: Topic :: Software Development :: Build Tools
Classifier: Topic :: Software Development :: Libraries :: Python Modules
Requires-Dist: datetime (>=5.5)
Requires-Dist: pywin32 (>=08)
